{
    "oil_id": "CC00149",
    "adios_data_model_version": "0.12.0",
    "metadata": {
        "name": "Cook Inlet",
        "source_id": "ODB00-150",
        "alternate_names": [
            "Unknown"
        ],
        "location": "Cook Inlet, Alaska, USA",
        "reference": {
            "year": 1979,
            "reference": "Rice, S.D., A. Moles, T.L. Taylor, and J.F. Karinen, \"Sensitivity of 39 Alaskan Marine Species to Cook Inlet Crude Oil and No. 2 Fuel Oil\", Proceedings of the 1979 Oil Spill Conference, American Petroleum Institute, Washington, D.C., pp. 549-554, 1979"
        },
        "product_type": "Crude Oil NOS",
        "model_completeness": 0,
        "gnome_suitable": false
    },
    "sub_samples": [
        {
            "metadata": {
                "name": "Fresh Oil Sample",
                "short_name": "Fresh Oil",
                "sample_id": "ODB00-150",
                "fraction_evaporated": {
                    "value": 0.0,
                    "unit": "%",
                    "unit_type": "massfraction"
                }
            }
        }
    ],
    "status": [
        "E030: Oils must have an API",
        "W006: No density values provided",
        "W100: Not GNOME compatible: Cannot initialize a Density object with no data"
    ],
    "review_status": {
        "status": "Not Reviewed"
    }
}